html2parquet_local.py
html2parquet_local_python.py
html2parquet_transform.py
html2parquet_transform_python.py
dpk_html2parquet_transform_python-0.2.1.dist-info/METADATA
dpk_html2parquet_transform_python-0.2.1.dist-info/WHEEL
dpk_html2parquet_transform_python-0.2.1.dist-info/top_level.txt
dpk_html2parquet_transform_python-0.2.1.dist-info/RECORD
